formatdetector/__init__.py
formatdetector/core.py
formatdetector/dicts.py
formatdetector-0.2.0.dist-info/LICENSE
formatdetector-0.2.0.dist-info/METADATA
formatdetector-0.2.0.dist-info/WHEEL
formatdetector-0.2.0.dist-info/top_level.txt
formatdetector-0.2.0.dist-info/RECORD
