Metadata-Version: 2.1
Name: formatdetector
Version: 0.2.0
Summary: A library that can easily find out the format of a binary file.
Home-page: https://github.com/AkagiYui/FormatDetector
Author: AkagiYui
Author-email: akagiyui@yeah.net
License: UNKNOWN
Platform: UNKNOWN
Classifier: Development Status :: 4 - Beta
Classifier: Programming Language :: Python :: 3.9
Classifier: Intended Audience :: Developers
Classifier: License :: OSI Approved :: MIT License
Classifier: Operating System :: OS Independent
Requires-Python: >=3.7
License-File: LICENSE
